clitr/__init__.py
clitr/main.py
clitr-0.2.0.dist-info/METADATA
clitr-0.2.0.dist-info/WHEEL
clitr-0.2.0.dist-info/entry_points.txt
clitr-0.2.0.dist-info/licenses/LICENSE
clitr-0.2.0.dist-info/RECORD
