Metadata-Version: 2.4
Name: clitr
Version: 0.2.0
Summary: CLI Translate - A tool to translate natural language to shell commands using LLMs
Project-URL: Homepage, https://github.com/jonte/clitr
Project-URL: Issues, https://github.com/jonte/clitr/issues
Author-email: Jonte <jonte@example.com>
License: MIT License
License-File: LICENSE
Requires-Python: >=3.9
Requires-Dist: litellm
Requires-Dist: pyperclip
